<?xml version="1.0" encoding="utf-8"?>
<r id="koikpv" xml:lang="koi">
 <lics xmlns:xhtml="http://www.w3.org/1999/xhtml" xml:space="preserve"><lic xml:lang="en">
This code is made available under a Creative Commons Attribution license
<a>http://creativecommons.org/licenses/by/3.0/no/deed.en</a>.

You are free to copy, distribute and adapt the work, as long as you always give
proper attribution using the attribution text below.

For the full license text, see the link above.</lic><ref>Work by Evgeni Tsypanov, Giellatekno at UiT, Divvun at the
 Norwegian Saami Parliament,
 and members of the language communities. Source code
 available at <a>https://victorio.uit.no/langtech/trunk/</a>.</ref>
     <sourcenote>
 THIS TEXT IS THE ORIGINAL SOURCE CODE. This is NOT a fully styled and
 published dictionary. As such it can and
 will contain unfinished entries, unpublished entries, entries with
 objectionable translations, etc. If you find any errors or want to add more
 words, download the file, edit it, and send it back to
 <a>mailto:feedback@divvun.no</a> and <a>mailto:giellatekno@hum.uit.no</a>.
 Please also note that the entries are not necessarily sorted,
 or could be wrongly sorted.

     </sourcenote></lics>


  <e>
    <lg>
      <l pos="Pron">кин</l>
      <stg>
        <st>кин</st>
      </stg>
    </lg>
    <mg>
      <tg xml:lang="kpv">
        <t pos="Pron">коді</t>
      </tg>
      <xg>
        <x>кинкӧт пантасит?</x>
        <xt xml:lang="kpv">кодкӧд паныдасинныд?</xt>
      </xg>
    </mg>
  </e>
  <e>
    <lg>
      <l pos="Pron">кинкӧ</l>
      <stg>
        <st>кинкӧ</st>
      </stg>
    </lg>
    <mg>
      <tg xml:lang="kpv">
        <t pos="Pron">кодкӧ</t>
      </tg>
      <xg>
        <x>кинкӧ пырис керкуас</x>
        <xt xml:lang="kpv">кодкӧ пырис керкаас</xt>
      </xg>
    </mg>
  </e>
  <e>
    <lg>
      <l pos="Pron">кӧда</l>
      <stg>
        <st>кӧда</st>
      </stg>
    </lg>
    <mg>
      <tg xml:lang="kpv">
        <t>коді</t>
      </tg>
      <xg>
        <x>кӧда мунӧ городас?</x>
        <xt xml:lang="kpv">коді мунӧ карас?</xt>
      </xg>
    </mg>
  </e>
  <e>
    <lg>
      <l pos="Pron">кӧдакӧ</l>
      <stg>
        <st>кӧдакӧ</st>
      </stg>
    </lg>
    <mg>
      <tg xml:lang="kpv">
        <t>кодкӧ</t>
        <t>кутшӧмкӧ</t>
      </tg>
      <xg>
        <x>кӧдакӧ васӧ ваялас</x>
        <xt xml:lang="kpv">кодкӧ ва ваялас</xt>
      </xg>
    </mg>
  </e>
  <e>
    <lg>
      <l pos="Pron">кӧдна</l>
      <stg>
        <st>кӧдна</st>
      </stg>
    </lg>
    <mg>
      <tg xml:lang="kpv">
        <t>кодъяс</t>
      </tg>
      <xg>
        <x>а нійӧ косьмӧм кӧзоккесӧ, кӧдна эшӧ веськыта сулалӧны, чуть вӧрзьӧтышт кинат – сэк жӧ пӧрасӧ</x>
        <src>(В.Баталов)</src>
        <xt/>
      </xg>
    </mg>
  </e>
  <e>
    <lg>
      <l pos="Pron">кӧдӧ</l>
      <stg>
        <st>кӧдӧ</st>
      </stg>
    </lg>
    <mg>
      <tg xml:lang="kpv">
        <t>кодӧс</t>
      </tg>
      <xg>
        <x>бордтыв, кӧдӧ неважын адззи берег дорісь</x>
        <src>(В.Баталов)</src>
        <xt xml:lang="kpv">ыджыд борд гӧн, кодӧс аддзи вадорысь</xt>
      </xg>
    </mg>
  </e>
  <e>
    <lg>
      <l pos="Pron">быдыс</l>
      <stg>
        <st>быдыс</st>
      </stg>
    </lg>
    <mg>
      <tg xml:lang="kpv">
        <t pos="Pron">быдӧн</t>
      </tg>
      <xg>
        <x>быдыс миян коласісь</x>
        <xt xml:lang="kpv">быдӧн миян пиысь</xt>
      </xg>
    </mg>
  </e>
  <e>
    <lg>
      <l pos="Pron">быдӧс</l>
      <stg>
        <st>быдӧс</st>
      </stg>
    </lg>
    <mg>
      <tg xml:lang="kpv">
        <t pos="Pron">ставыс</t>
        <t pos="Pron">став</t>
        <t pos="Pron">быдтор</t>
      </tg>
      <xg>
        <x>сы киись быдӧс петӧ</x>
        <xt xml:lang="kpv">сы киын ставыс артмӧ</xt>
      </xg>
    </mg>
  </e>

</r>
